hellofire/__init__.py
hellofire/hari.py
bemagnetized-1.0.dist-info/METADATA
bemagnetized-1.0.dist-info/WHEEL
bemagnetized-1.0.dist-info/top_level.txt
bemagnetized-1.0.dist-info/RECORD
