Metadata-Version: 2.1
Name: bemagnetized
Version: 1.0
Summary: prints fire
Home-page: UNKNOWN
License: UNKNOWN
Platform: UNKNOWN
